converter_csv/__about__.py
converter_csv/__init__.py
converter_csv/__main__.py
converter_csv/_version.py
converter_csv/app.py
converter_csv/ico_generator.py
converter_csv/ldcc_ico.py
converter_csv/utilities.py
converter_csv/dialogs/__init__.py
converter_csv/dialogs/about.py
converter_csv/dialogs/update_check.py
converter_csv/dialogs/url_open.py
converter_csv/ui/__init__.py
converter_csv/ui/mainwindow.py
converter_csv-0.5.0.dist-info/licenses/LICENSE
converter_csv-0.5.0.dist-info/METADATA
converter_csv-0.5.0.dist-info/WHEEL
converter_csv-0.5.0.dist-info/entry_points.txt
converter_csv-0.5.0.dist-info/top_level.txt
converter_csv-0.5.0.dist-info/RECORD
